{
    "dates": [
        {
            "date": "2024-09-29",
            "tags": [
                "online"
            ]
        },
        {
            "date": "2024-10-06",
            "tags": [
                "online",
                "offline"
            ]
        },
        {
            "date": "2024-10-13",
            "tags": [
                "online",
                "offline"
            ]
        },
        {
            "date": "2024-10-20",
            "tags": [
                "online",
                "offline"
            ]
        },
        {
            "date": "2024-10-27",
            "tags": [
                "online",
                "offline"
            ]
        },
        {
            "date": "2024-11-10",
            "tags": [
                "online",
                "offline"
            ]
        },
        {
            "date": "2024-11-24",
            "tags": [
                "online",
                "offline"
            ]
        },
        {
            "date": "2024-12-08",
            "tags": [
                "online",
                "offline"
            ]
        },
        {
            "date": "2024-12-15",
            "tags": [
                "online",
                "offline"
            ]
        },
        {
            "date": "2025-01-19",
            "tags": [
                "online",
                "offline"
            ]
        },
        {
            "date": "2025-02-02",
            "tags": [
                "online",
                "offline"
            ]
        },
        {
            "date": "2025-02-23",
            "tags": [
                "online",
                "offline"
            ]
        },
        {
            "date": "2025-03-16",
            "tags": [
                "online",
                "offline"
            ]
        },
        {
            "date": "2025-03-30",
            "tags": [
                "online",
                "offline"
            ]
        }
    ]
}
